irm_kmi_api/__init__.py
irm_kmi_api/api.py
irm_kmi_api/const.py
irm_kmi_api/data.py
irm_kmi_api/pollen.py
irm_kmi_api/rain_graph.py
irm_kmi_api/resources/__init__.py
irm_kmi_api/resources/be_black.py
irm_kmi_api/resources/be_satellite.py
irm_kmi_api/resources/be_white.py
irm_kmi_api/resources/nl.py
irm_kmi_api/resources/roboto.py
irm_kmi_api-1.1.1.dist-info/licenses/LICENSE
irm_kmi_api-1.1.1.dist-info/METADATA
irm_kmi_api-1.1.1.dist-info/WHEEL
irm_kmi_api-1.1.1.dist-info/top_level.txt
irm_kmi_api-1.1.1.dist-info/RECORD
