Metadata-Version: 2.4
Name: irm-kmi-api
Version: 1.1.1
Summary: Retrieve data from the Belgian IRM KMI in Python
Author-email: Jules Dejaeghere <curable.grass491@mailer.me>
License: MIT License
Project-URL: Homepage, https://github.com/jdejaegh/irm-kmi-api
Keywords: weather,weather-api,netherlands,weather-forecast,pollen,belgium,luxembourg,rain-radar
Classifier: License :: OSI Approved :: Apache Software License
Classifier: Programming Language :: Python
Classifier: Programming Language :: Python :: 3
Requires-Python: >=3.12
License-File: LICENSE
Requires-Dist: aiohttp<4.0.0,>=3.11.0
Requires-Dist: svgwrite<2.0.0,>=1.4.3
Dynamic: license-file
